{
  "stream_id": "bili-bv1od",
  "chunk_id": "chunk_0004",
  "seq": 4,
  "start": 900.0,
  "end": 1200.0,
  "transcript_texts": [
    "记得那天，小阳见到莎拉之后就一直在叨叨，总感觉面熟。",
    "他好像很久之前就见过莎拉",
    "可惜想了好几天还是没想起来,到底在哪看见过",
    "案发之后，靳远曾在网络上搜索有关巴多奥的帖子。",
    "他按时间顺序检索",
    "发现最早的一条说买到巴多奥包包的帖子竟然是在5年前发布的",
    "可是那个时候国内都还没有引进这个品牌",
    "这位名叫青苔女神的用户是怎么买到巴多奥的呢？",
    "靳远于是请网站协助调查",
    "帮他确认青苔女神的身份",
    "警队队长则研究起了案发地",
    "发现尸体的地方是清潭洞奢侈品一条街",
    "这里每个街区有几十个监控",
    "可仍然没有拍到凶手弃尸",
    "这种情况只有一个可能",
    "凶手是通过下水道搬运尸体",
    "为找到第一案发现场",
    "队长戴着防毒面具",
    "亲自跳下下水道寻找出口",
    "另一边，小杨通过视频催眠总算想起来",
    "他在三月百货的员工特惠活动上见过莎拉。",
    "当时，他无意中拍到过他的脸。",
    "被发现后,对方直接过来抢手机删照片",
    "现在，旧手机里还留有一张照片",
    "可惜还是没有看到脸，只有脚踝处的纹身。",
    "与此同时，网站也查到了倾谈女生的真实身份。",
    "她与小杨见过的是同一个人",
    "所以莎拉并不是什么美极寒衣",
    "她也不是含着金汤匙出生",
    "她跟小宇小羊一样来自底层",
    "因为害怕被认出来",
    "所以故意把泄露客户信息的责任推到小宇身上",
    "借此把他们赶出奢侈品圈",
    "警队队长在下水道一通摸索",
    "最后发现通道的另一端正是三越百货的垃圾站",
    "所有线索全部汇集到了这个商场",
    "五年前",
    "莎拉曾以穆加希的身份在这里工作",
    "五年后",
    "她引进的巴多奥在韩国爆火",
    "根据小宇的说辞",
    "莎拉死前一直致力于让巴多奥入住三越百货商场",
    "而在她死后",
    "发现尸体的下水道就连着商场",
    "这一切会不会与三越百货的董事长有关呢？",
    "是她杀了莎拉",
    "又借助商场的下水道弃尸吗",
    "两名警察立刻去找董事长。",
    "希望他配合调查",
    "然而，董事长以证据不充分为由拒绝合作。",
    "没办法",
    "对方是韩国最富有的人",
    "警方确实不能随便动他",
    "一旦出现三月百货董事长涉及凶杀的新闻",
    "股市立刻被波及",
    "如若只是个误会",
    "谁来担责",
    "警方现在也无法获取上场的监控。",
    "除非有确凿的证据申请到搜查令",
    "调查一下子陷入僵局",
    "两人只能回到禁区",
    "看看从穆家希这个身份下手",
    "会不会有其他进展",
    "提到这个名字",
    "有名警员突然想起",
    "他以前在分局工作时听到过这个人",
    "他曾是在逃诈骗犯",
    "还被全网通缉",
    "那正是五年前",
    "轰动一时的青台女神卷款跑路案",
    "案卷记载穆加希以倾谈女神这个昵称",
    "在网络上出售二手奢侈品",
    "获得买方信任之后",
    "她在某天突然取走共计5亿的预付款",
    "直接卷钱跑路",
    "但这宗案件最终以穆加希死亡结案。",
    "5年前监控清晰地拍到她跳桥自杀",
    "临死前还包着一款闪亮亮的名牌包",
    "警方找到她的住所",
    "屋内堆砌着大量发卖的二手奢侈品",
    "还有一封遗书",
    "不过案卷上并没有记录打捞到尸体",
    "当时负责调查的警方",
    "仅凭监控就判断自杀",
    "因为后续也没有找到穆加希的踪迹",
    "一个人活着总会去医院，去银行。",
    "但是都没有",
    "这桩案件便就此了结",
    "队长推测",
    "穆加希可能是伪造自杀",
    "借此逃债",
    "她死之后再以沙拉的身份继续生活",
    "未搞清楚5年前究竟发生了什么",
    "队长偷拿了那封遗书",
    "上面记录着一段不为人知的过去",
    "5年前,穆加希来到3月百后的Prada门店当起销售",
    "在这里,他深刻体会到了阶层差距",
    "作为销售,他们不能使用门店的卫生间",
    "也不能乘坐商场的池梯或手扶梯",
    "上下班必须走员工通道,不能与顾客冲撞",
    "在上班期间,如若想上厕所也不能说出卫生间这几个字眼",
    "他们得说去休息一下",
    "规矩如此之多，穆加希还是很向往这份工作。",
    "因为他喜欢奢侈品,他想在此扎根",
    "有一天上班",
    "穆加希偶然看到了",
    "对面的迪奥",
    "展示了新款包包",
    "它如此美丽",
    "如此耀眼",
    "看到它的一瞬间",
    "穆加希正在思考",
    "他一定要成为",
    "配得上这只包的人",
    "怀着这个梦想",
    "他更加努力工作",
    "可是 灭顶之灾突如其来",
    "某天，门店遭遇盗窃。",
    "而那个时间刚好是穆加希当班",
    "当时已经快关门 店里没有顾客",
    "Mujiaxi憋了一整天，总算有空去厕所。",
    "可就在这个空档",
    "有人进来偷走大量衣物 箱包",
    "只要讓你使用廁所",
    "就不會發生这種事了",
    "如果要去工作人员的卫生间",
    "我还得一圈一圈地走",
    "肚臍疙瘩"
  ],
  "timeline_texts": [
    "记得那天，小阳见到莎拉之后就一直在叨叨，总感觉面熟。",
    "他好像很久之前就见过莎拉",
    "可惜想了好几天还是没想起来,到底在哪看见过",
    "案发之后，靳远曾在网络上搜索有关巴多奥的帖子。",
    "他按时间顺序检索",
    "发现最早的一条说买到巴多奥包包的帖子竟然是在5年前发布的",
    "可是那个时候国内都还没有引进这个品牌",
    "这位名叫青苔女神的用户是怎么买到巴多奥的呢？",
    "靳远于是请网站协助调查",
    "帮他确认青苔女神的身份",
    "警队队长则研究起了案发地",
    "发现尸体的地方是清潭洞奢侈品一条街",
    "这里每个街区有几十个监控",
    "可仍然没有拍到凶手弃尸",
    "这种情况只有一个可能",
    "凶手是通过下水道搬运尸体",
    "为找到第一案发现场",
    "队长戴着防毒面具",
    "亲自跳下下水道寻找出口",
    "另一边，小杨通过视频催眠总算想起来",
    "他在三月百货的员工特惠活动上见过莎拉。",
    "当时，他无意中拍到过他的脸。",
    "被发现后,对方直接过来抢手机删照片",
    "现在，旧手机里还留有一张照片",
    "可惜还是没有看到脸，只有脚踝处的纹身。",
    "与此同时，网站也查到了倾谈女生的真实身份。",
    "她与小杨见过的是同一个人",
    "所以莎拉并不是什么美极寒衣",
    "她也不是含着金汤匙出生",
    "她跟小宇小羊一样来自底层",
    "因为害怕被认出来",
    "所以故意把泄露客户信息的责任推到小宇身上",
    "借此把他们赶出奢侈品圈",
    "警队队长在下水道一通摸索",
    "最后发现通道的另一端正是三越百货的垃圾站",
    "所有线索全部汇集到了这个商场",
    "五年前",
    "莎拉曾以穆加希的身份在这里工作",
    "五年后",
    "她引进的巴多奥在韩国爆火",
    "根据小宇的说辞",
    "莎拉死前一直致力于让巴多奥入住三越百货商场",
    "而在她死后",
    "发现尸体的下水道就连着商场",
    "这一切会不会与三越百货的董事长有关呢？",
    "是她杀了莎拉",
    "又借助商场的下水道弃尸吗",
    "两名警察立刻去找董事长。",
    "希望他配合调查",
    "然而，董事长以证据不充分为由拒绝合作。",
    "没办法",
    "对方是韩国最富有的人",
    "警方确实不能随便动他",
    "一旦出现三月百货董事长涉及凶杀的新闻",
    "股市立刻被波及",
    "如若只是个误会",
    "谁来担责",
    "警方现在也无法获取上场的监控。",
    "除非有确凿的证据申请到搜查令",
    "调查一下子陷入僵局",
    "两人只能回到禁区",
    "看看从穆家希这个身份下手",
    "会不会有其他进展",
    "提到这个名字",
    "有名警员突然想起",
    "他以前在分局工作时听到过这个人",
    "他曾是在逃诈骗犯",
    "还被全网通缉",
    "那正是五年前",
    "轰动一时的青台女神卷款跑路案",
    "案卷记载穆加希以倾谈女神这个昵称",
    "在网络上出售二手奢侈品",
    "获得买方信任之后",
    "她在某天突然取走共计5亿的预付款",
    "直接卷钱跑路",
    "但这宗案件最终以穆加希死亡结案。",
    "5年前监控清晰地拍到她跳桥自杀",
    "临死前还包着一款闪亮亮的名牌包",
    "警方找到她的住所",
    "屋内堆砌着大量发卖的二手奢侈品",
    "还有一封遗书",
    "不过案卷上并没有记录打捞到尸体",
    "当时负责调查的警方",
    "仅凭监控就判断自杀",
    "因为后续也没有找到穆加希的踪迹",
    "一个人活着总会去医院，去银行。",
    "但是都没有",
    "这桩案件便就此了结",
    "队长推测",
    "穆加希可能是伪造自杀",
    "借此逃债",
    "她死之后再以沙拉的身份继续生活",
    "未搞清楚5年前究竟发生了什么",
    "队长偷拿了那封遗书",
    "上面记录着一段不为人知的过去",
    "5年前,穆加希来到3月百后的Prada门店当起销售",
    "在这里,他深刻体会到了阶层差距",
    "作为销售,他们不能使用门店的卫生间",
    "也不能乘坐商场的池梯或手扶梯",
    "上下班必须走员工通道,不能与顾客冲撞",
    "在上班期间,如若想上厕所也不能说出卫生间这几个字眼",
    "他们得说去休息一下",
    "规矩如此之多，穆加希还是很向往这份工作。",
    "因为他喜欢奢侈品,他想在此扎根",
    "有一天上班",
    "穆加希偶然看到了",
    "对面的迪奥",
    "展示了新款包包",
    "它如此美丽",
    "如此耀眼",
    "看到它的一瞬间",
    "穆加希正在思考",
    "他一定要成为",
    "配得上这只包的人",
    "怀着这个梦想",
    "他更加努力工作",
    "可是 灭顶之灾突如其来",
    "某天，门店遭遇盗窃。",
    "而那个时间刚好是穆加希当班",
    "当时已经快关门 店里没有顾客",
    "Mujiaxi憋了一整天，总算有空去厕所。",
    "可就在这个空档",
    "有人进来偷走大量衣物 箱包",
    "只要讓你使用廁所",
    "就不會發生这種事了",
    "如果要去工作人员的卫生间",
    "我还得一圈一圈地走",
    "肚臍疙瘩"
  ],
  "metadata": {
    "unit_count": 128
  }
}